{
  "favorites": [
    {
      "thumbnail": {
        "path": "http://i.annihil.us/u/prod/marvel/i/mg/3/20/5232158de5b16",
        "extension": "jpg"
      },
      "idCharacter": 1017100,
      "name": "A-Bomb (HAS)",
      "nickname": "fernando.amazingweb",
      "favorite": true,
      "id": 1
    },
    {
      "thumbnail": {
        "path": "http://i.annihil.us/u/prod/marvel/i/mg/f/60/4c0042121d790",
        "extension": "jpg"
      },
      "idCharacter": 1009150,
      "name": "Agent Zero",
      "nickname": "fernando.amazingweb",
      "favorite": true,
      "id": 3
    }
  ]
}